rrc_mapdata_parser/__init__.py
rrc_mapdata_parser/ingest.py
rrc_mapdata_parser/lookups.py
rrc_mapdata_parser/parser.py
rrc_mapdata_parser/rrc_parser.py
rrc_mapdata_parser-0.1.0.dist-info/licenses/LICENSE
rrc_mapdata_parser-0.1.0.dist-info/METADATA
rrc_mapdata_parser-0.1.0.dist-info/WHEEL
rrc_mapdata_parser-0.1.0.dist-info/top_level.txt
rrc_mapdata_parser-0.1.0.dist-info/RECORD
