Metadata-Version: 2.4
Name: rrc-mapdata-parser
Version: 0.1.0
Summary: Python module to ingest and process Texas Railroad Commission (RRC) Digital Map Information from .zip archives
Author-email: Marcus Salinas <marcus@example.com>
License: MIT
Project-URL: Homepage, https://github.com/jippylong12/rrc-mapdata-parser
Project-URL: Repository, https://github.com/jippylong12/rrc-mapdata-parser
Project-URL: Issues, https://github.com/jippylong12/rrc-mapdata-parser/issues
Keywords: rrc,gis,shapefile,texas,oil,gas,wells,railroad-commission,petroleum
Classifier: Development Status :: 3 - Alpha
Classifier: Intended Audience :: Developers
Classifier: Intended Audience :: Science/Research
Classifier: License :: OSI Approved :: MIT License
Classifier: Operating System :: OS Independent
Classifier: Programming Language :: Python :: 3
Classifier: Programming Language :: Python :: 3.10
Classifier: Programming Language :: Python :: 3.11
Classifier: Programming Language :: Python :: 3.12
Classifier: Topic :: Scientific/Engineering :: GIS
Classifier: Topic :: Scientific/Engineering :: Information Analysis
Classifier: Typing :: Typed
Requires-Python: >=3.10
License-File: LICENSE
Requires-Dist: pyshp>=2.3.0
Requires-Dist: dbfread>=2.0.7
Requires-Dist: shapely>=2.0.0
Provides-Extra: dev
Requires-Dist: pytest>=7.0.0; extra == "dev"
Requires-Dist: pytest-cov>=4.0.0; extra == "dev"
Requires-Dist: build; extra == "dev"
Requires-Dist: twine; extra == "dev"
Dynamic: license-file
